{
  "_class": "symbolInstance",
  "booleanOperation": 0,
  "do_objectID": "E7E73244-FD90-4AA5-BAC4-42BAA0253DBB",
  "exportOptions": {
    "_class": "exportOptions",
    "do_objectID": "4245A26F-D761-4888-9BA1-BD0E1ACC09BF",
    "exportFormats": [
    ],
    "includedLayerIds": [
    ],
    "layerOptions": 0,
    "shouldTrim": false
  },
  "frame": {
    "_class": "rect",
    "constrainProportions": true,
    "do_objectID": "BFAA88C9-2CFE-40DB-8B8C-D1CBA7B03BCC",
    "height": 24,
    "width": 24,
    "x": 33,
    "y": 5
  },
  "horizontalSpacing": 0,
  "isFixedToViewport": false,
  "isFlippedHorizontal": false,
  "isFlippedVertical": false,
  "isLocked": false,
  "isVisible": true,
  "layerListExpandedType": 0,
  "name": "🔘 Icon",
  "nameIsFixed": true,
  "overrideValues": [
  ],
  "resizingConstraint": 37,
  "resizingType": 0,
  "rotation": 0,
  "scale": 1,
  "shouldBreakMaskChain": false,
  "style": {
    "_class": "style",
    "contextSettings": {
      "_class": "graphicsContextSettings",
      "blendMode": 0,
      "do_objectID": "F8106A32-08E7-4EF0-8CDF-F563EAAAFC62",
      "opacity": 0.6
    },
    "do_objectID": "67A2119C-A127-4045-B3C1-A652A7488BB7",
    "endMarkerType": 0,
    "miterLimit": 10,
    "startMarkerType": 0,
    "windingRule": 1
  },
  "symbolID": "D3C8E7B2-8105-4016-A45D-05B89E7D93A2",
  "verticalSpacing": 0
}