{
  "_class": "group",
  "booleanOperation": 0,
  "do_objectID": "02A3B3A9-7061-4AFF-93BC-D3277DA00215",
  "exportOptions": {
    "_class": "exportOptions",
    "do_objectID": "3421B58C-D6D7-442A-A0F6-F31944A526F4",
    "exportFormats": [
    ],
    "includedLayerIds": [
    ],
    "layerOptions": 0,
    "shouldTrim": false
  },
  "frame": {
    "_class": "rect",
    "constrainProportions": false,
    "do_objectID": "3C1E04CF-9B71-413C-BF9D-632C48F5DC43",
    "height": 55,
    "width": 134,
    "x": 112,
    "y": 24
  },
  "hasClickThrough": false,
  "isFixedToViewport": false,
  "isFlippedHorizontal": false,
  "isFlippedVertical": false,
  "isLocked": false,
  "isVisible": true,
  "layerListExpandedType": 2,
  "layers": [
    {
      "class": "group",
      "id": "0C499010-2E6B-4EE3-94EB-4710A752F7D4"
    }
  ],
  "name": "Group 3",
  "nameIsFixed": false,
  "resizingConstraint": 63,
  "resizingType": 0,
  "rotation": 0,
  "shouldBreakMaskChain": false,
  "style": {
    "_class": "style",
    "do_objectID": "9C647123-5CCF-4B15-AE83-0F9BC62A51C0",
    "endMarkerType": 0,
    "miterLimit": 10,
    "startMarkerType": 0,
    "windingRule": 1
  }
}