{
  "_class": "symbolInstance",
  "booleanOperation": 0,
  "do_objectID": "E27E54FD-1EAF-4433-8045-8E93FF90653B",
  "exportOptions": {
    "_class": "exportOptions",
    "do_objectID": "7FD812F2-784F-4BB8-9FB2-E7E25067407D",
    "exportFormats": [
    ],
    "includedLayerIds": [
    ],
    "layerOptions": 0,
    "shouldTrim": false
  },
  "frame": {
    "_class": "rect",
    "constrainProportions": false,
    "do_objectID": "7DDF6BE5-13D9-4F3C-9181-8F453543C40B",
    "height": 23,
    "width": 23,
    "x": 16.19895116832686,
    "y": 39.70406403526445
  },
  "horizontalSpacing": 0,
  "isFixedToViewport": false,
  "isFlippedHorizontal": false,
  "isFlippedVertical": false,
  "isLocked": false,
  "isVisible": true,
  "layerListExpandedType": 0,
  "name": "Icons/Hardware/keyboard_arrow_left",
  "nameIsFixed": false,
  "overrideValues": [
    {
      "_class": "overrideValue",
      "do_objectID": "6B4E2307-3804-492B-B06A-C92E1CAD9924",
      "overrideName": "E78AD601-02AC-47F1-9175-89DA84AA688C_symbolID",
      "value": "FA5328AC-26BB-4665-AF82-F18DD9B7AFED"
    }
  ],
  "resizingConstraint": 9,
  "resizingType": 0,
  "rotation": 1,
  "scale": 1,
  "shouldBreakMaskChain": false,
  "style": {
    "_class": "style",
    "do_objectID": "EB36091F-905D-4C1B-86C9-441A66460D60",
    "endMarkerType": 0,
    "miterLimit": 10,
    "startMarkerType": 0,
    "windingRule": 1
  },
  "symbolID": "C11E86C0-1588-40D1-A5CC-394ABE81BFF8",
  "verticalSpacing": 0
}