{
  "_class": "symbolInstance",
  "booleanOperation": 0,
  "do_objectID": "89592DC9-1CF8-44DA-99DC-5CE896A84E4E",
  "exportOptions": {
    "_class": "exportOptions",
    "do_objectID": "188C1DE3-8D73-4C6D-96D7-DD1F58911769",
    "exportFormats": [
    ],
    "includedLayerIds": [
    ],
    "layerOptions": 0,
    "shouldTrim": false
  },
  "frame": {
    "_class": "rect",
    "constrainProportions": false,
    "do_objectID": "3E1B8797-1516-4D53-937D-FC3F24D3135F",
    "height": 24,
    "width": 24,
    "x": 15,
    "y": 10
  },
  "horizontalSpacing": 0,
  "isFixedToViewport": false,
  "isFlippedHorizontal": false,
  "isFlippedVertical": false,
  "isLocked": false,
  "isVisible": true,
  "layerListExpandedType": 0,
  "name": "Icons/Communications/forum",
  "nameIsFixed": false,
  "overrideValues": [
    {
      "_class": "overrideValue",
      "overrideName": "875E062D-A6F2-4A0C-A2CD-637A11C9282C_symbolID",
      "value": "FA5328AC-26BB-4665-AF82-F18DD9B7AFED"
    },
    {
      "_class": "overrideValue",
      "do_objectID": "B8A8B664-FFDE-4033-9F14-BCA1BF608C52",
      "overrideName": "30338BC0-94A1-4865-9B7F-F95B0AF19695_symbolID",
      "value": "832190EE-4C78-42F6-89F2-DC3A33E13049"
    }
  ],
  "resizingConstraint": 25,
  "resizingType": 0,
  "rotation": 0,
  "scale": 1,
  "shouldBreakMaskChain": false,
  "style": {
    "_class": "style",
    "do_objectID": "14DE6703-7D35-48C5-B39D-D4597510B3A2",
    "endMarkerType": 0,
    "miterLimit": 10,
    "startMarkerType": 0,
    "windingRule": 1
  },
  "symbolID": "370B62FC-6B07-46A7-B738-DC6FECA212BC",
  "verticalSpacing": 0
}