{
  "_class": "symbolInstance",
  "booleanOperation": 0,
  "do_objectID": "11E2BD91-5D28-4AD5-9B69-F03F68CD5DDA",
  "exportOptions": {
    "_class": "exportOptions",
    "do_objectID": "3502A1EA-05FD-4195-8E1D-9AE7DA004C84",
    "exportFormats": [
    ],
    "includedLayerIds": [
    ],
    "layerOptions": 0,
    "shouldTrim": false
  },
  "frame": {
    "_class": "rect",
    "constrainProportions": true,
    "do_objectID": "5FCA91A4-D097-472A-85E1-6EB82C1FED66",
    "height": 24,
    "width": 24,
    "x": 32,
    "y": 0.6499996185302734
  },
  "horizontalSpacing": 0,
  "isFixedToViewport": false,
  "isFlippedHorizontal": false,
  "isFlippedVertical": false,
  "isLocked": false,
  "isVisible": true,
  "layerListExpandedType": 0,
  "name": "🔘 Icon",
  "nameIsFixed": true,
  "overrideValues": [
  ],
  "resizingConstraint": 37,
  "resizingType": 0,
  "rotation": 0,
  "scale": 1,
  "shouldBreakMaskChain": false,
  "style": {
    "_class": "style",
    "contextSettings": {
      "_class": "graphicsContextSettings",
      "blendMode": 0,
      "do_objectID": "BB2FF5C0-FA31-435D-8419-EA34E8EF53C4",
      "opacity": 0.6
    },
    "do_objectID": "4079B592-7861-4B70-AFD5-7EE556865E83",
    "endMarkerType": 0,
    "miterLimit": 10,
    "startMarkerType": 0,
    "windingRule": 1
  },
  "symbolID": "24BF0630-E10A-470D-863D-55717FA9DA06",
  "verticalSpacing": 0
}