{
  "_class": "group",
  "booleanOperation": 0,
  "do_objectID": "69282958-E08A-4B2E-AC95-12511FAA3D28",
  "exportOptions": {
    "_class": "exportOptions",
    "do_objectID": "40489F8A-CA48-4E85-A102-BF804D9341CA",
    "exportFormats": [
    ],
    "includedLayerIds": [
    ],
    "layerOptions": 0,
    "shouldTrim": false
  },
  "frame": {
    "_class": "rect",
    "constrainProportions": false,
    "do_objectID": "656ADB5E-47EB-4F3C-98EB-8BE79640A90B",
    "height": 83,
    "width": 319,
    "x": 0,
    "y": 0
  },
  "hasClickThrough": false,
  "isFixedToViewport": false,
  "isFlippedHorizontal": false,
  "isFlippedVertical": false,
  "isLocked": false,
  "isVisible": true,
  "layerListExpandedType": 2,
  "layers": [
    {
      "class": "group",
      "id": "27F3C17C-BD88-4338-996B-849EB74FB4FC"
    },
    {
      "class": "group",
      "id": "D7393D47-C2EC-4DBE-BFB0-1B673C593483"
    }
  ],
  "name": "Cards/Vaga Busca",
  "nameIsFixed": false,
  "resizingConstraint": 63,
  "resizingType": 0,
  "rotation": 0,
  "shouldBreakMaskChain": false,
  "style": {
    "_class": "style",
    "do_objectID": "85C2B7C9-2A41-46A9-B717-BA0ACAD81DB9",
    "endMarkerType": 0,
    "miterLimit": 10,
    "startMarkerType": 0,
    "windingRule": 1
  }
}