{
  "_class": "shapePath",
  "booleanOperation": -1,
  "do_objectID": "9FADE7AB-7E54-4908-B413-467A6DFA6AF3",
  "edited": true,
  "exportOptions": {
    "_class": "exportOptions",
    "do_objectID": "D38828F6-004F-45EA-B1E8-D394EA4D7C8B",
    "exportFormats": [
    ],
    "includedLayerIds": [
    ],
    "layerOptions": 0,
    "shouldTrim": false
  },
  "frame": {
    "_class": "rect",
    "constrainProportions": false,
    "do_objectID": "5823AFB1-71AB-4294-BDEA-34205D37C373",
    "height": 12.29225980576351,
    "width": 16.35308762945492,
    "x": 0,
    "y": 0
  },
  "isClosed": true,
  "isFixedToViewport": false,
  "isFlippedHorizontal": false,
  "isFlippedVertical": false,
  "isLocked": false,
  "isVisible": true,
  "layerListExpandedType": 0,
  "name": "SVGID_3_-path",
  "nameIsFixed": false,
  "pointRadiusBehaviour": 0,
  "points": [
    {
      "_class": "curvePoint",
      "cornerRadius": 0,
      "curveFrom": "{0, 0}",
      "curveMode": 1,
      "curveTo": "{0, 0}",
      "hasCurveFrom": false,
      "hasCurveTo": false,
      "point": "{0, 0}"
    },
    {
      "_class": "curvePoint",
      "cornerRadius": 0,
      "curveFrom": "{0.49999999999999828, 1}",
      "curveMode": 1,
      "curveTo": "{0.49999999999999828, 1}",
      "hasCurveFrom": false,
      "hasCurveTo": false,
      "point": "{0.49999999999999828, 1}"
    },
    {
      "_class": "curvePoint",
      "cornerRadius": 0,
      "curveFrom": "{1, 0}",
      "curveMode": 1,
      "curveTo": "{1, 0}",
      "hasCurveFrom": false,
      "hasCurveTo": false,
      "point": "{1, 0}"
    }
  ],
  "resizingConstraint": 63,
  "resizingType": 0,
  "rotation": 0,
  "shouldBreakMaskChain": false
}