{
  "_class": "shapeGroup",
  "booleanOperation": 0,
  "clippingMaskMode": 0,
  "do_objectID": "4DDEF110-9E34-4E3D-8B1C-2BDC53AB0254",
  "exportOptions": {
    "_class": "exportOptions",
    "do_objectID": "DAD840BC-0217-48E9-80AE-AEF8C0C153F1",
    "exportFormats": [
    ],
    "includedLayerIds": [
    ],
    "layerOptions": 0,
    "shouldTrim": false
  },
  "frame": {
    "_class": "rect",
    "constrainProportions": false,
    "do_objectID": "495464CF-06FE-4600-A83F-19D2CDEC10AA",
    "height": 14.01627906976753,
    "width": 17.40540540540535,
    "x": 11.34459459459458,
    "y": 7.319612403100791
  },
  "hasClickThrough": false,
  "hasClippingMask": false,
  "isFixedToViewport": false,
  "isFlippedHorizontal": false,
  "isFlippedVertical": false,
  "isLocked": false,
  "isVisible": true,
  "layerListExpandedType": 0,
  "layers": [
    {
      "class": "rectangle",
      "id": "9197C3B5-5A61-4BF4-AA1B-220557FF28B0"
    },
    {
      "class": "rectangle",
      "id": "317B1F73-84BE-4D7A-860C-E92739429631"
    },
    {
      "class": "rectangle",
      "id": "1DEDFBBF-2A45-446F-857A-6FFE99619BD7"
    }
  ],
  "name": "Combined Shape",
  "nameIsFixed": false,
  "resizingConstraint": 63,
  "resizingType": 0,
  "rotation": 0,
  "shouldBreakMaskChain": false,
  "style": {
    "_class": "style",
    "blur": {
      "_class": "blur",
      "center": "{0.5, 0.5}",
      "do_objectID": "C1C1A239-8072-443F-A39F-4DA1618AA963",
      "isEnabled": false,
      "motionAngle": 0,
      "radius": 2,
      "type": 0
    },
    "borders": [
      {
        "_class": "border",
        "color": {
          "_class": "color",
          "alpha": 1,
          "blue": 0.592,
          "green": 0.592,
          "red": 0.592
        },
        "fillType": 0,
        "isEnabled": false,
        "position": 1,
        "thickness": 0.5
      }
    ],
    "do_objectID": "A6064244-2161-40D8-97FC-3E9E33AB58A4",
    "endMarkerType": 0,
    "fills": [
      {
        "_class": "fill",
        "color": {
          "_class": "color",
          "alpha": 1,
          "blue": 0.6549019607843137,
          "green": 0.6549019607843137,
          "red": 0.6549019607843137
        },
        "fillType": 0,
        "isEnabled": true,
        "noiseIndex": 0,
        "noiseIntensity": 0,
        "patternFillType": 0,
        "patternTileScale": 1
      }
    ],
    "miterLimit": 10,
    "startMarkerType": 0,
    "windingRule": 1
  },
  "windingRule": 1
}