{
  "_class": "group",
  "booleanOperation": 0,
  "do_objectID": "ACD6A175-C495-4DC0-A896-5CEF18D28C61",
  "exportOptions": {
    "_class": "exportOptions",
    "do_objectID": "22A625B7-AEC3-410E-877B-0E06DF9A8C31",
    "exportFormats": [
    ],
    "includedLayerIds": [
    ],
    "layerOptions": 0,
    "shouldTrim": false
  },
  "frame": {
    "_class": "rect",
    "constrainProportions": false,
    "do_objectID": "07B835F9-D377-4835-81E3-D27FE1D825AB",
    "height": 5,
    "width": 11,
    "x": 275,
    "y": 47
  },
  "hasClickThrough": false,
  "isFixedToViewport": false,
  "isFlippedHorizontal": false,
  "isFlippedVertical": false,
  "isLocked": false,
  "isVisible": true,
  "layerListExpandedType": 2,
  "layers": [
    {
      "class": "group",
      "id": "54301F2C-3B82-4E4C-B856-5B368D25B433"
    }
  ],
  "name": "Group 6",
  "nameIsFixed": false,
  "resizingConstraint": 63,
  "resizingType": 0,
  "rotation": 0,
  "shouldBreakMaskChain": false,
  "style": {
    "_class": "style",
    "do_objectID": "40334B70-2152-43B1-AC15-ABE8581417F7",
    "endMarkerType": 0,
    "miterLimit": 10,
    "startMarkerType": 0,
    "windingRule": 1
  }
}