{
  "_class": "shapeGroup",
  "booleanOperation": -1,
  "clippingMaskMode": 0,
  "do_objectID": "0E4909A7-9083-46A5-9B43-EC4B5DE7B296",
  "exportOptions": {
    "_class": "exportOptions",
    "do_objectID": "1EB281EF-B915-452C-88F2-4928A59EFF8B",
    "exportFormats": [
    ],
    "includedLayerIds": [
    ],
    "layerOptions": 0,
    "shouldTrim": false
  },
  "frame": {
    "_class": "rect",
    "constrainProportions": false,
    "do_objectID": "A6A48CD7-F446-4794-9D09-B87C73D1ECE1",
    "height": 98.5399061032864,
    "width": 18.39622641509435,
    "x": 55.89622641509433,
    "y": 51.75117370892019
  },
  "hasClickThrough": false,
  "hasClippingMask": false,
  "isFixedToViewport": false,
  "isFlippedHorizontal": false,
  "isFlippedVertical": false,
  "isLocked": false,
  "isVisible": true,
  "layerListExpandedType": 1,
  "layers": [
    {
      "class": "shapePath",
      "id": "E3AAC976-4809-4704-8044-266950652089"
    }
  ],
  "name": "Fill 16",
  "nameIsFixed": false,
  "resizingConstraint": 63,
  "resizingType": 0,
  "rotation": 0,
  "shouldBreakMaskChain": false,
  "style": {
    "_class": "style",
    "do_objectID": "01790A8C-56A5-4E92-854A-61D4C7460A3D",
    "endMarkerType": 0,
    "fills": [
      {
        "_class": "fill",
        "color": {
          "_class": "color",
          "alpha": 1,
          "blue": 0.498,
          "green": 0.8200000000000001,
          "red": 0.98
        },
        "fillType": 0,
        "isEnabled": true,
        "noiseIndex": 0,
        "noiseIntensity": 0,
        "patternFillType": 1,
        "patternTileScale": 1
      }
    ],
    "miterLimit": 10,
    "startMarkerType": 0,
    "windingRule": 1
  },
  "windingRule": 1
}